RemoveMedia/__init__.py
RemoveMedia/__main__.py
RemoveMedia/configuration/__init__.py
RemoveMedia/configuration/generate_config.py
RemoveMedia/configuration/log.py
RemoveMedia/configuration/mask_config.py
RemoveMedia/configuration/read_config.py
RemoveMedia/manipulation/__init__.py
RemoveMedia/manipulation/base.py
RemoveMedia/manipulation/remove.py
RemoveMedia/notification/__init__.py
RemoveMedia/notification/pbullet.py
RemoveMedia/notification/plex.py
RemoveMedia-0.0.3.dist-info/LICENSE
RemoveMedia-0.0.3.dist-info/METADATA
RemoveMedia-0.0.3.dist-info/WHEEL
RemoveMedia-0.0.3.dist-info/top_level.txt
RemoveMedia-0.0.3.dist-info/RECORD
