Metadata-Version: 2.1
Name: RemoveMedia
Version: 0.0.3
Summary: An application to remove file and folder in a given directory for a given treshold 
Home-page: https://github.com/Hatoris/RemoveMedia
Author: Florian Bernard
Author-email: florianxbernard@gmail.com
License: MIT
Project-URL: Documentation, https://hatoris.github.io/RemoveMedia/html/index.html
Project-URL: Source, https://github.com/Hatoris/RemoveMedia
Keywords: filemanagement,datetime
Platform: UNKNOWN
Classifier: Programming Language :: Python :: 3.6
Classifier: Development Status :: 3 - Alpha
Classifier: Natural Language :: English
Classifier: License :: OSI Approved :: MIT License
Requires-Python: >=3.6
Requires-Dist: pendulum (>=2.0.2)
Requires-Dist: fire (>=0.1.3)
Requires-Dist: pushbullet.py (>=0.11.0)
